{"_ts":[1577845117,1577932483,1578019707],"_r":{"breakdown":{"html":{"bytes":[670,670,670],"requests":[1,1,1]},"js":{"bytes":[205479,205606,205527],"requests":[1,1,1]},"css":{"bytes":[3305,3305,3305],"requests":[2,2,2]},"image":{"bytes":[239824,239824,239824],"requests":[7,7,7]},"flash":{"bytes":[0,0,0],"requests":[0,0,0]},"font":{"bytes":[29312,29312,29312],"requests":[2,2,2]},"video":{"bytes":[0,0,0],"requests":[0,0,0]},"other":{"bytes":[72508,72508,72509],"requests":[3,3,3]}},"date":[1577845117,1577932483,1578019707],"domElements":[463,463,463],"domInteractive":[1846,1833,1002],"firstPaint":[2046.2950000001,1921.1049999994,1162.5600000007],"fullyLoaded":[3995,4144,3146],"id":["200101_4Q_ea2eb49e3cd9d32a3915258a4fec9a31","200102_2X_35bb902788b0c30c88da0884fd95676c","200103_DY_9a0daade41e66608ad8d7e67fa3a98e2"],"loadTime":[2168,2024,1280],"render":[2100,1900,1200],"SpeedIndex":[4310,4047,3257],"TTFB":[826,839,287],"videoFrames":[[{"_i":"ms_000000.jpg","_t":0,"_vc":0},{"_i":"ms_002100.jpg","_t":2100,"_vc":23},{"_i":"ms_002200.jpg","_t":2200,"_vc":23},{"_i":"ms_002300.jpg","_t":2300,"_vc":24},{"_i":"ms_002400.jpg","_t":2400,"_vc":23},{"_i":"ms_004100.jpg","_t":4100,"_vc":24},{"_i":"ms_004900.jpg","_t":4900,"_vc":37},{"_i":"ms_005000.jpg","_t":5000,"_vc":100}],[{"_i":"ms_000000.jpg","_t":0,"_vc":0},{"_i":"ms_001900.jpg","_t":1900,"_vc":23},{"_i":"ms_002000.jpg","_t":2000,"_vc":23},{"_i":"ms_002200.jpg","_t":2200,"_vc":24},{"_i":"ms_002300.jpg","_t":2300,"_vc":23},{"_i":"ms_003900.jpg","_t":3900,"_vc":24},{"_i":"ms_004700.jpg","_t":4700,"_vc":100}],[{"_i":"ms_000000.jpg","_t":0,"_vc":0},{"_i":"ms_001200.jpg","_t":1200,"_vc":23},{"_i":"ms_001300.jpg","_t":1300,"_vc":24},{"_i":"ms_001500.jpg","_t":1500,"_vc":23},{"_i":"ms_003200.jpg","_t":3200,"_vc":24},{"_i":"ms_003800.jpg","_t":3800,"_vc":37},{"_i":"ms_003900.jpg","_t":3900,"_vc":100}]],"visualComplete":[5000,4700,3900],"lighthouse":[27,27,27],"pagespeed":[94,92,95]}}